pysomneo/__init__.py
pysomneo/api.py
pysomneo/const.py
pysomneo/somneo.py
pysomneo/util.py
pysomneo-5.0.1.dist-info/licenses/LICENSE
pysomneo-5.0.1.dist-info/METADATA
pysomneo-5.0.1.dist-info/WHEEL
pysomneo-5.0.1.dist-info/top_level.txt
pysomneo-5.0.1.dist-info/RECORD
