Metadata-Version: 2.4
Name: pysomneo
Version: 5.0.1
Summary: A library to communicate with the API of Philips Somneo.
Author-email: Ruud van der Horst <pypi@mail.ruudvdhorst.nl>
License:  GNU GENERAL PUBLIC LICENSE
Project-URL: Homepage, https://github.com/theneweinstein/pysomneo
Project-URL: Bug Tracker, https://github.com/theneweinstein/pysomneo/issues
Classifier: Programming Language :: Python :: 3
Classifier: License :: OSI Approved :: GNU General Public License v3 or later (GPLv3+)
Classifier: Operating System :: OS Independent
Requires-Python: >=3.7
License-File: LICENSE
Dynamic: license-file
